jdatetimext/__init__.py
jdatetimext/convert.py
jdatetimext/jdate_utils.py
jdatetimext/version.py
jdatetimext-1.1.1.dist-info/METADATA
jdatetimext-1.1.1.dist-info/WHEEL
jdatetimext-1.1.1.dist-info/top_level.txt
jdatetimext-1.1.1.dist-info/RECORD
